cpskin/__init__.py
cpskin/slider/__init__.py
cpskin/slider/configure.zcml
cpskin/slider/interfaces.py
cpskin/slider/testing.py
cpskin/slider/testing.zcml
cpskin/slider/browser/__init__.py
cpskin/slider/browser/collection_slick_view.pt
cpskin/slider/browser/collection_slider_dx_view.pt
cpskin/slider/browser/collection_slider_view_vertical.pt
cpskin/slider/browser/configure.zcml
cpskin/slider/browser/static/blank.gif
cpskin/slider/portlets/__init__.py
cpskin/slider/portlets/configure.zcml
cpskin/slider/portlets/slider_collection.py
cpskin/slider/portlets/slidercollectionportlet.pt
cpskin/slider/profiles/default/browserlayer.xml
cpskin/slider/profiles/default/cssregistry.xml
cpskin/slider/profiles/default/jsregistry.xml
cpskin/slider/profiles/default/metadata.xml
cpskin/slider/profiles/default/portlets.xml
cpskin/slider/profiles/default/types/Collection.xml
cpskin/slider/profiles/testing/metadata.xml
cpskin/slider/profiles/uninstall/browserlayer.xml
cpskin/slider/profiles/uninstall/cssregistry.xml
cpskin/slider/profiles/uninstall/portlets.xml
cpskin/slider/profiles/uninstall/types/Collection.xml
cpskin/slider/resources/css/ajax-loader.gif
cpskin/slider/resources/css/flexslider.css
cpskin/slider/resources/css/slick.css
cpskin/slider/resources/css/slider-pro.css
cpskin/slider/resources/css/sliderfix.css
cpskin/slider/resources/css/fonts/flexslider-icon.eot
cpskin/slider/resources/css/fonts/flexslider-icon.svg
cpskin/slider/resources/css/fonts/flexslider-icon.ttf
cpskin/slider/resources/css/fonts/flexslider-icon.woff
cpskin/slider/resources/css/fonts/next.svg
cpskin/slider/resources/css/fonts/prev.svg
cpskin/slider/resources/images/bg_play_pause.png
cpskin/slider/resources/images/blank.gif
cpskin/slider/resources/javascript/cpskin.slick.js
cpskin/slider/resources/javascript/cpskin.slider.js
cpskin/slider/resources/javascript/jquery.flexslider-min.js
cpskin/slider/resources/javascript/jquery.sliderpro.js
cpskin.slider-1.2.11.dist-info/DESCRIPTION.rst
cpskin.slider-1.2.11.dist-info/METADATA
cpskin.slider-1.2.11.dist-info/RECORD
cpskin.slider-1.2.11.dist-info/WHEEL
cpskin.slider-1.2.11.dist-info/metadata.json
cpskin.slider-1.2.11.dist-info/top_level.txt
