Metadata-Version: 2.0
Name: cpskin.slider
Version: 1.2.11
Summary: Slider package for cpskin
Home-page: https://github.com/imio/
Author: IMIO
Author-email: support@imio.be
License: gpl
Platform: UNKNOWN
Classifier: Environment :: Web Environment
Classifier: Programming Language :: Python
Classifier: Programming Language :: Python :: 2.7
Classifier: Framework :: Plone
Classifier: Framework :: Plone :: 4.2
Classifier: Framework :: Plone :: 4.3
Provides-Extra: test
Requires-Dist: setuptools
Requires-Dist: Plone
Requires-Dist: plone.api
Requires-Dist: cpskin.locales
Requires-Dist: cpskin.core
Provides-Extra: test
Requires-Dist: plone.api; extra == 'test'
Requires-Dist: plone.app.robotframework; extra == 'test'
Requires-Dist: plone.app.testing; extra == 'test'
